teradataml/LICENSE-3RD-PARTY.pdf
teradataml/LICENSE.pdf
teradataml/README.md
teradataml/__init__.py
teradataml/_version.py
teradataml/analytics/Transformations.py
teradataml/analytics/__init__.py
teradataml/analytics/analytic_function_executor.py
teradataml/analytics/analytic_query_generator.py
teradataml/analytics/meta_class.py
teradataml/analytics/utils.py
teradataml/analytics/valib.py
teradataml/analytics/byom/H2OPredict.py
teradataml/analytics/byom/PMMLPredict.py
teradataml/analytics/byom/__init__.py
teradataml/analytics/json_parser/__init__.py
teradataml/analytics/json_parser/analytic_functions_argument.py
teradataml/analytics/json_parser/json_store.py
teradataml/analytics/json_parser/metadata.py
teradataml/analytics/json_parser/utils.py
teradataml/analytics/sqle/DecisionTreePredict.py
teradataml/analytics/sqle/NaiveBayesPredict.py
teradataml/analytics/sqle/__init__.py
teradataml/analytics/sqle/json/decisiontreepredict_sqle.json
teradataml/analytics/sqle/json/naivebayespredict_sqle.json
teradataml/analytics/table_operator/__init__.py
teradataml/analytics/uaf/__init__.py
teradataml/automl/__init__.py
teradataml/automl/custom_json_utils.py
teradataml/automl/data_preparation.py
teradataml/automl/data_transformation.py
teradataml/automl/feature_engineering.py
teradataml/automl/feature_exploration.py
teradataml/automl/model_evaluation.py
teradataml/automl/model_training.py
teradataml/automl/autodataprep/__init__.py
teradataml/catalog/__init__.py
teradataml/catalog/byom.py
teradataml/catalog/function_argument_mapper.py
teradataml/catalog/model_cataloging_utils.py
teradataml/clients/__init__.py
teradataml/clients/auth_client.py
teradataml/clients/keycloak_client.py
teradataml/clients/pkce_client.py
teradataml/common/__init__.py
teradataml/common/aed_utils.py
teradataml/common/bulk_exposed_utils.py
teradataml/common/constants.py
teradataml/common/deprecations.py
teradataml/common/exceptions.py
teradataml/common/formula.py
teradataml/common/garbagecollector.py
teradataml-20.0.0.9.dist-info/METADATA
teradataml-20.0.0.9.dist-info/WHEEL
teradataml-20.0.0.9.dist-info/top_level.txt
teradataml-20.0.0.9.dist-info/zip-safe
teradataml-20.0.0.9.dist-info/RECORD
