Metadata-Version: 2.1
Name: teradataml
Version: 20.0.0.9
Summary: Teradata Vantage Python package for Advanced Analytics
Home-page: http://www.teradata.com/
Author: Teradata Corporation
License: Teradata License Agreement
Keywords: Teradata
Platform: MacOS X, Windows, Linux
Classifier: Programming Language :: Python :: 3 :: Only
Classifier: Programming Language :: Python :: 3.8
Classifier: Programming Language :: Python :: 3.9
Classifier: Operating System :: Microsoft :: Windows
Classifier: Operating System :: MacOS :: MacOS X
Classifier: Operating System :: POSIX :: Linux
Classifier: Topic :: Database :: Front-Ends
Classifier: License :: Other/Proprietary License
Requires-Python: >=3.8
Requires-Dist: teradatasql (>=20.0.0.26)
Requires-Dist: teradatasqlalchemy (>=20.0.0.9)
Requires-Dist: pandas (>=0.22)
Requires-Dist: psutil
Requires-Dist: requests (>=2.25.1)
Requires-Dist: pyjwt (>=2.8.0)
Requires-Dist: cryptography (>=42.0.5)
Requires-Dist: sqlalchemy (>=2.0)
Requires-Dist: python-dotenv
Requires-Dist: oauthlib (>=3.2.2)
Requires-Dist: requests-oauthlib (>=2.0.0)
Requires-Dist: pydantic (>=2.10.6)
Requires-Dist: PyYAML (>=6.0.2)
Provides-Extra: automl
Requires-Dist: imbalanced-learn (>=0.8.0) ; extra == 'automl'
Requires-Dist: scikit-learn (>=0.24.2) ; extra == 'automl'
Provides-Extra: eda-ui
Requires-Dist: teradatamlwidgets (>=20.0.0.5) ; extra == 'eda-ui'
Provides-Extra: openml
Requires-Dist: scikit-learn (>=0.24.2) ; extra == 'openml'
Requires-Dist: lightgbm (>=3.3.3) ; extra == 'openml'
Provides-Extra: visualization
Requires-Dist: matplotlib (>=3.7.5) ; extra == 'visualization'
Requires-Dist: seaborn (>=0.13.0) ; extra == 'visualization'
